owlipy/__init__.py
owlipy/constants.py
owlipy/exceptions.py
owlipy/owl.py
owlipy/owl_interface.py
owlipy/types.py
owlipy/wrappers/__init__.py
owlipy/wrappers/cplex/__init__.py
owlipy/wrappers/cplex/cplex_mapper.py
owlipy/wrappers/cplex/cplex_wrapper.py
owlipy/wrappers/debug/__init__.py
owlipy/wrappers/debug/debug_wrapper.py
owlipy/wrappers/gurobi/__init__.py
owlipy/wrappers/gurobi/gurobi_mapper.py
owlipy/wrappers/gurobi/gurobi_wrapper.py
owlipy/wrappers/highs/__init__.py
owlipy/wrappers/highs/highs_mapper.py
owlipy/wrappers/highs/highs_wrapper.py
owlipy-0.0.2.dist-info/LICENSE
owlipy-0.0.2.dist-info/METADATA
owlipy-0.0.2.dist-info/WHEEL
owlipy-0.0.2.dist-info/top_level.txt
owlipy-0.0.2.dist-info/RECORD
