Metadata-Version: 2.1
Name: owlipy
Version: 0.0.2
Summary: Present mathematical equality and inequality in symbol format.
Author-email: Pouya Motakef <p.motakef@gmail.com>
Maintainer-email: Pouya Motakef <p.motakef@gmail.com>
License: BSD 2-Clause License
Project-URL: Homepage, https://github.com/pmotakef/owlipy
Project-URL: Documentation, https://github.com/pmotakef/owlipy
Project-URL: Repository, https://github.com/pmotakef/owlipy
Project-URL: Issues, https://github.com/pmotakef/owlipy/issues
Project-URL: Changelog, https://github.com/pmotakef/owlipy/blob/main/CHANGELOG.md
Keywords: symbol
Requires-Python: >=3.10
License-File: LICENSE
Requires-Dist: symbolipy
Provides-Extra: dev
Requires-Dist: pytest; extra == "dev"
Requires-Dist: gurobipy; extra == "dev"
Requires-Dist: docplex; extra == "dev"
Requires-Dist: highspy; extra == "dev"
